urn/__init__.py
urn/cli.py
urn/computation.py
urn/constants.py
urn/constraint.py
urn/evaluation.py
urn/grammar.lark
urn/output.py
urn/parsing.py
urn/shell.py
urn_calculator-0.0.1.dist-info/LICENSE
urn_calculator-0.0.1.dist-info/METADATA
urn_calculator-0.0.1.dist-info/WHEEL
urn_calculator-0.0.1.dist-info/entry_points.txt
urn_calculator-0.0.1.dist-info/top_level.txt
urn_calculator-0.0.1.dist-info/RECORD
