Metadata-Version: 2.1
Name: urn-calculator
Version: 0.0.1
Summary: Multivariate hypergeometric command line calculator.
Author: Alex Riley
License: MIT License
Project-URL: Homepage, https://github.com/ajcr/urn
Keywords: calculator,probability,count,draw,random,sample,hypergeometric
Classifier: Development Status :: 3 - Alpha
Classifier: Topic :: Scientific/Engineering :: Mathematics
Classifier: Topic :: Scientific/Engineering :: Visualization
Classifier: Topic :: Utilities
Classifier: Typing :: Typed
Classifier: Intended Audience :: Science/Research
Classifier: License :: OSI Approved :: MIT License
Classifier: Programming Language :: Python :: 3.10
Classifier: Programming Language :: Python :: 3.11
Classifier: Programming Language :: Python :: 3.12
Requires-Python: >=3.10
License-File: LICENSE
Requires-Dist: lark >=1.1.5
Requires-Dist: sympy >=1.12
Requires-Dist: tabulate >=0.9.0
Requires-Dist: uniplot >=0.10.0
Provides-Extra: dev
Requires-Dist: pytest ; extra == 'dev'
Requires-Dist: ruff ; extra == 'dev'
